ashai/__init__.py
ashai/chunker.py
ashai/llm_api.py
ashai/ollam_api.py
ashai/test.py
ashai/utils.py
ashai-0.1.3.dist-info/licenses/LICENSE
ashai-0.1.3.dist-info/METADATA
ashai-0.1.3.dist-info/WHEEL
ashai-0.1.3.dist-info/top_level.txt
ashai-0.1.3.dist-info/RECORD
