Metadata-Version: 2.4
Name: ashai
Version: 0.1.3
Summary: AshAI: Intelligent agentic chunking by Ashay
Author-email: Ashay <ashayka68@gmail.com>
Requires-Python: >=3.8
License-File: LICENSE
Requires-Dist: requests
Requires-Dist: python-dotenv
Requires-Dist: rich
Requires-Dist: nltk
Requires-Dist: PyMuPDF
Requires-Dist: openai
Dynamic: license-file
